gemseo_hexaly/__init__.py
gemseo_hexaly/algos/__init__.py
gemseo_hexaly/algos/opt/__init__.py
gemseo_hexaly/algos/opt/hexaly/__init__.py
gemseo_hexaly/algos/opt/hexaly/hexaly.py
gemseo_hexaly/algos/opt/hexaly/hexaly_settings.py
gemseo_hexaly/algos/opt/hexaly/_core/__init__.py
gemseo_hexaly/algos/opt/hexaly/_core/hexaly_callback.py
gemseo_hexaly/algos/opt/hexaly/_core/hexaly_function.py
gemseo_hexaly-1.1.1.dist-info/licenses/LICENSE.txt
gemseo_hexaly-1.1.1.dist-info/METADATA
gemseo_hexaly-1.1.1.dist-info/WHEEL
gemseo_hexaly-1.1.1.dist-info/entry_points.txt
gemseo_hexaly-1.1.1.dist-info/top_level.txt
gemseo_hexaly-1.1.1.dist-info/RECORD
